MANIFEST.in
README.rst
setup.py
git_dlist.egg-info/PKG-INFO
git_dlist.egg-info/SOURCES.txt
git_dlist.egg-info/dependency_links.txt
git_dlist.egg-info/entry_points.txt
git_dlist.egg-info/requires.txt
git_dlist.egg-info/top_level.txt
gitdlist/__init__.py