Metadata-Version: 1.0
Name: git-dlist
Version: 0.1
Summary: Small tool to keep a directory of git repositories in sync.
Home-page: http://github.com/mbr/gitlist
Author: Marc Brinkmann
Author-email: git@marcbrinkmann.de
License: MIT
Platform: UNKNOWN
